DreamNBT/__init__.py
DreamNBT/entities.py
DreamNBT/snbt.py
dreamnbt-0.1.4.dist-info/METADATA
dreamnbt-0.1.4.dist-info/WHEEL
dreamnbt-0.1.4.dist-info/licenses/LICENSE
dreamnbt-0.1.4.dist-info/RECORD
