Metadata-Version: 2.4
Name: DreamNBT
Version: 0.1.4
Summary: 一个Minecraft基岩版NBT解析工具
Project-URL: Homepage, https://github.com/old-dream321/DreamNBT
Author-email: old-dream321 <hzz123123@outlook.com>
License:                                  Apache License
License-File: LICENSE
Requires-Python: >=3.8
